odoo/addons/sale_commission/README.rst
odoo/addons/sale_commission/__init__.py
odoo/addons/sale_commission/__manifest__.py
odoo/addons/sale_commission/demo/sale_agent_demo.xml
odoo/addons/sale_commission/i18n/ca.po
odoo/addons/sale_commission/i18n/de.po
odoo/addons/sale_commission/i18n/es.po
odoo/addons/sale_commission/i18n/es_AR.po
odoo/addons/sale_commission/i18n/fr.po
odoo/addons/sale_commission/i18n/it.po
odoo/addons/sale_commission/i18n/nl_NL.po
odoo/addons/sale_commission/i18n/pt.po
odoo/addons/sale_commission/i18n/pt_BR.po
odoo/addons/sale_commission/i18n/pt_PT.po
odoo/addons/sale_commission/i18n/sale_commission.pot
odoo/addons/sale_commission/i18n/sl.po
odoo/addons/sale_commission/i18n/zh_CN.po
odoo/addons/sale_commission/migrations/14.0.1.3.0/pre-migration.py
odoo/addons/sale_commission/models/__init__.py
odoo/addons/sale_commission/models/account_move.py
odoo/addons/sale_commission/models/product_template.py
odoo/addons/sale_commission/models/res_partner.py
odoo/addons/sale_commission/models/sale_commission.py
odoo/addons/sale_commission/models/sale_commission_mixin.py
odoo/addons/sale_commission/models/sale_order.py
odoo/addons/sale_commission/models/settlement.py
odoo/addons/sale_commission/readme/CONFIGURE.rst
odoo/addons/sale_commission/readme/CONTRIBUTORS.rst
odoo/addons/sale_commission/readme/DESCRIPTION.rst
odoo/addons/sale_commission/readme/ROADMAP.rst
odoo/addons/sale_commission/readme/USAGE.rst
odoo/addons/sale_commission/report/__init__.py
odoo/addons/sale_commission/report/sale_commission_analysis_report.py
odoo/addons/sale_commission/report/sale_commission_analysis_report_view.xml
odoo/addons/sale_commission/security/ir.model.access.csv
odoo/addons/sale_commission/security/sale_commission_security.xml
odoo/addons/sale_commission/static/description/icon.png
odoo/addons/sale_commission/static/description/icon.svg
odoo/addons/sale_commission/static/description/index.html
odoo/addons/sale_commission/tests/__init__.py
odoo14_addon_sale_commission-14.0.1.10.2.dist-info/METADATA
odoo14_addon_sale_commission-14.0.1.10.2.dist-info/WHEEL
odoo14_addon_sale_commission-14.0.1.10.2.dist-info/top_level.txt
odoo14_addon_sale_commission-14.0.1.10.2.dist-info/RECORD
