Metadata-Version: 2.1
Name: odoo14-addon-sale_commission
Version: 14.0.1.10.2
Summary: Sales commissions
Home-page: https://github.com/OCA/commission
Author: Tecnativa,Odoo Community Association (OCA)
Author-email: support@odoo-community.org
License: AGPL-3
Classifier: Programming Language :: Python
Classifier: Framework :: Odoo
Classifier: Framework :: Odoo :: 14.0
Classifier: License :: OSI Approved :: GNU Affero General Public License v3
Classifier: Development Status :: 6 - Mature
Requires-Python: >=3.6
Requires-Dist: odoo<14.1dev,>=14.0a
